trytond/modules/nereid_webshop/__init__.py
trytond/modules/nereid_webshop/carrier.py
trytond/modules/nereid_webshop/carrier.xml
trytond/modules/nereid_webshop/checkout.py
trytond/modules/nereid_webshop/cms.xml
trytond/modules/nereid_webshop/forms.py
trytond/modules/nereid_webshop/invoice.py
trytond/modules/nereid_webshop/message.xml
trytond/modules/nereid_webshop/party.py
trytond/modules/nereid_webshop/product.py
trytond/modules/nereid_webshop/sale.py
trytond/modules/nereid_webshop/tree.py
trytond/modules/nereid_webshop/tree.xml
trytond/modules/nereid_webshop/tryton.cfg
trytond/modules/nereid_webshop/webshop.py
trytond/modules/nereid_webshop/webshop.xml
trytond/modules/nereid_webshop/website.py
trytond/modules/nereid_webshop/locale/ca.po
trytond/modules/nereid_webshop/locale/de.po
trytond/modules/nereid_webshop/locale/es.po
trytond/modules/nereid_webshop/static/css/bootstrap-theme.css
trytond/modules/nereid_webshop/static/css/bootstrap-theme.css.map
trytond/modules/nereid_webshop/static/css/bootstrap-theme.min.css
trytond/modules/nereid_webshop/static/css/bootstrap.css
trytond/modules/nereid_webshop/static/css/bootstrap.css.map
trytond/modules/nereid_webshop/static/css/bootstrap.min.css
trytond/modules/nereid_webshop/static/css/font-awesome.min.css
trytond/modules/nereid_webshop/static/css/font-open-sans.css
trytond/modules/nereid_webshop/static/css/jquery.bxslider.css
trytond/modules/nereid_webshop/static/css/lightbox.css
trytond/modules/nereid_webshop/static/css/nereid.css
trytond/modules/nereid_webshop/static/css/owl.carousel.css
trytond/modules/nereid_webshop/static/css/pnotify.custom.min.css
trytond/modules/nereid_webshop/static/css/style.css
trytond/modules/nereid_webshop/static/css/typeaheadjs.css
trytond/modules/nereid_webshop/static/fonts/FontAwesome.otf
trytond/modules/nereid_webshop/static/fonts/fontawesome-webfont.eot
trytond/modules/nereid_webshop/static/fonts/fontawesome-webfont.svg
trytond/modules/nereid_webshop/static/fonts/fontawesome-webfont.ttf
m9s_nereid_webshop-7.0.5.dist-info/LICENSE
m9s_nereid_webshop-7.0.5.dist-info/METADATA
m9s_nereid_webshop-7.0.5.dist-info/WHEEL
m9s_nereid_webshop-7.0.5.dist-info/entry_points.txt
m9s_nereid_webshop-7.0.5.dist-info/top_level.txt
m9s_nereid_webshop-7.0.5.dist-info/RECORD
