Metadata-Version: 2.2
Name: m9s_nereid_webshop
Version: 7.0.5
Summary: Tryton Nereid Webshop Module
Home-page: https://www.m9s.biz/
Download-URL: https://gitlab.com/m9s/nereid_webshop.git
Author: MBSolutions
Author-email: info@m9s.biz
License: GPL-3
Project-URL: Bug Tracker, https://support.m9s.biz/
Project-URL: Source Code, https://gitlab.com/m9s/nereid_webshop.git
Classifier: Development Status :: 5 - Production/Stable
Classifier: Environment :: Plugins
Classifier: Framework :: Tryton
Classifier: Intended Audience :: Developers
Classifier: Intended Audience :: Financial and Insurance Industry
Classifier: Intended Audience :: Legal Industry
Classifier: License :: OSI Approved :: GNU General Public License v3 or later (GPLv3+)
Classifier: Natural Language :: Bulgarian
Classifier: Natural Language :: Catalan
Classifier: Natural Language :: Chinese (Simplified)
Classifier: Natural Language :: Czech
Classifier: Natural Language :: Dutch
Classifier: Natural Language :: English
Classifier: Natural Language :: Finnish
Classifier: Natural Language :: French
Classifier: Natural Language :: German
Classifier: Natural Language :: Hungarian
Classifier: Natural Language :: Indonesian
Classifier: Natural Language :: Italian
Classifier: Natural Language :: Persian
Classifier: Natural Language :: Polish
Classifier: Natural Language :: Portuguese (Brazilian)
Classifier: Natural Language :: Romanian
Classifier: Natural Language :: Russian
Classifier: Natural Language :: Slovenian
Classifier: Natural Language :: Spanish
Classifier: Natural Language :: Turkish
Classifier: Natural Language :: Ukrainian
Classifier: Operating System :: OS Independent
Classifier: Programming Language :: Python :: 3
Classifier: Programming Language :: Python :: 3.8
Classifier: Programming Language :: Python :: 3.9
Classifier: Programming Language :: Python :: 3.10
Classifier: Programming Language :: Python :: 3.11
Classifier: Programming Language :: Python :: 3.12
Classifier: Programming Language :: Python :: Implementation :: CPython
Classifier: Topic :: Office/Business
Requires-Python: >=3.8
License-File: LICENSE
Requires-Dist: MarkupSafe
Requires-Dist: trytond_carrier<7.1,>=7.0
Requires-Dist: m9s_gift_card<7.1,>=7.0
Requires-Dist: m9s_nereid_catalog<7.1,>=7.0
Requires-Dist: m9s_nereid_catalog_tree<7.1,>=7.0
Requires-Dist: m9s_nereid_cart_b2c<7.1,>=7.0
Requires-Dist: m9s_nereid_checkout<7.1,>=7.0
Requires-Dist: m9s_nereid_cms<7.1,>=7.0
Requires-Dist: m9s_nereid_image_transformation<7.1,>=7.0
Requires-Dist: m9s_nereid_wishlist<7.1,>=7.0
Requires-Dist: trytond_party<7.1,>=7.0
Requires-Dist: m9s_stock_package_rate<7.1,>=7.0
Requires-Dist: m9s-trytond<7.1,>=7.0
Provides-Extra: test
Requires-Dist: cssutils; extra == "test"
Requires-Dist: m9s-nereid-catalog-variants<7.1,>=7.0; extra == "test"
Requires-Dist: m9s-sale-discount<7.1,>=7.0; extra == "test"
Requires-Dist: pycountry; extra == "test"
Requires-Dist: pygeoip; extra == "test"
Requires-Dist: trytond-sale-shipment-cost<7.1,>=7.0; extra == "test"
Dynamic: author
Dynamic: author-email
Dynamic: classifier
Dynamic: description
Dynamic: description-content-type
Dynamic: download-url
Dynamic: home-page
Dynamic: keywords
Dynamic: license
Dynamic: project-url
Dynamic: provides-extra
Dynamic: requires-dist
Dynamic: requires-python
Dynamic: summary
